oneNeuron/__init__.py
oneNeuron/perceptron.py
oneNeuron_pypi_tripathimanoj-0.0.8.dist-info/LICENSE
oneNeuron_pypi_tripathimanoj-0.0.8.dist-info/METADATA
oneNeuron_pypi_tripathimanoj-0.0.8.dist-info/WHEEL
oneNeuron_pypi_tripathimanoj-0.0.8.dist-info/top_level.txt
oneNeuron_pypi_tripathimanoj-0.0.8.dist-info/RECORD
