Metadata-Version: 2.1
Name: oneNeuron-pypi-tripathimanoj
Version: 0.0.8
Summary: Its a implimentation of Perceptron
Home-page: https://github.com/tripathimanoj/oneNeuron_pypi
Author: tripathimanoj
Author-email: tripathimanoj220@gmail.com
License: UNKNOWN
Project-URL: Bug Tracker, https://github.com/tripathimanoj/oneNeuron_pypi/issues
Platform: UNKNOWN
Classifier: Programming Language :: Python :: 3
Classifier: License :: OSI Approved :: MIT License
Classifier: Operating System :: OS Independent
Requires-Python: >=3.7
License-File: LICENSE
Requires-Dist: numpy
Requires-Dist: tqdm
